odoo/addons/l10n_ro_stock_account_date/README.rst
odoo/addons/l10n_ro_stock_account_date/__init__.py
odoo/addons/l10n_ro_stock_account_date/__manifest__.py
odoo/addons/l10n_ro_stock_account_date/i18n/l10n_ro_stock_account_date.pot
odoo/addons/l10n_ro_stock_account_date/i18n/ro.po
odoo/addons/l10n_ro_stock_account_date/models/__init__.py
odoo/addons/l10n_ro_stock_account_date/models/account_move.py
odoo/addons/l10n_ro_stock_account_date/models/stock_move.py
odoo/addons/l10n_ro_stock_account_date/models/stock_move_line.py
odoo/addons/l10n_ro_stock_account_date/models/stock_picking.py
odoo/addons/l10n_ro_stock_account_date/models/stock_valuation_layer.py
odoo/addons/l10n_ro_stock_account_date/readme/CONTRIBUTORS.rst
odoo/addons/l10n_ro_stock_account_date/readme/DESCRIPTION.rst
odoo/addons/l10n_ro_stock_account_date/readme/INSTALL.rst
odoo/addons/l10n_ro_stock_account_date/static/description/icon.png
odoo/addons/l10n_ro_stock_account_date/static/description/index.html
odoo/addons/l10n_ro_stock_account_date/static/src/css/report.css
odoo/addons/l10n_ro_stock_account_date/tests/__init__.py
odoo/addons/l10n_ro_stock_account_date/tests/test_stock_accounting_date.py
odoo/addons/l10n_ro_stock_account_date/views/stock_picking_views.xml
odoo/addons/l10n_ro_stock_account_date/views/stock_valuation_layer_views.xml
odoo14_addon_l10n_ro_stock_account_date-14.0.2.7.0.dist-info/METADATA
odoo14_addon_l10n_ro_stock_account_date-14.0.2.7.0.dist-info/WHEEL
odoo14_addon_l10n_ro_stock_account_date-14.0.2.7.0.dist-info/top_level.txt
odoo14_addon_l10n_ro_stock_account_date-14.0.2.7.0.dist-info/RECORD
